anonymeter/__init__.py
anonymeter/evaluators/__init__.py
anonymeter/evaluators/inference_evaluator.py
anonymeter/evaluators/linkability_evaluator.py
anonymeter/evaluators/singling_out_evaluator.py
anonymeter/neighbors/__init__.py
anonymeter/neighbors/mixed_types_kneighbors.py
anonymeter/preprocessing/__init__.py
anonymeter/preprocessing/transformations.py
anonymeter/preprocessing/type_detection.py
anonymeter/stats/__init__.py
anonymeter/stats/confidence.py
anonymeter-1.0.0.dist-info/LICENSE.md
anonymeter-1.0.0.dist-info/METADATA
anonymeter-1.0.0.dist-info/WHEEL
anonymeter-1.0.0.dist-info/top_level.txt
anonymeter-1.0.0.dist-info/RECORD
