Metadata-Version: 2.1
Name: anonymeter
Version: 1.0.0
Summary: Measure singling out, linkability, and inference risk for synthetic data.
Author-email: Statice GmbH <hello@statice.ai>
License: The Clear BSD License
Project-URL: Homepage, https://github.com/statice/anonymeter
Project-URL: Bug Tracker, https://github.com/statice/anonymeter/issues
Project-URL: Changelog, https://github.com/statice/anonymeter/blob/main/CHANGELOG.md
Classifier: Programming Language :: Python :: 3
Classifier: License :: OSI Approved :: BSD License
Classifier: Operating System :: OS Independent
Requires-Python: <3.12,>3.7
License-File: LICENSE.md
Requires-Dist: scikit-learn ~=1.2
Requires-Dist: numpy <1.27,>=1.22
Requires-Dist: pandas >=1.4
Requires-Dist: joblib ~=1.2
Requires-Dist: numba ~=0.58
Provides-Extra: dev
Requires-Dist: ruff ~=0.1.14 ; extra == 'dev'
Requires-Dist: mypy ~=1.8.0 ; extra == 'dev'
Requires-Dist: pre-commit ~=3.5 ; extra == 'dev'
Requires-Dist: pytest ~=7.4 ; extra == 'dev'
Requires-Dist: build ~=0.10 ; extra == 'dev'
Requires-Dist: twine ~=4.0 ; extra == 'dev'
Provides-Extra: notebooks
Requires-Dist: jupyterlab ~=3.4 ; extra == 'notebooks'
Requires-Dist: matplotlib ~=3.5 ; extra == 'notebooks'
Requires-Dist: seaborn ~=0.11 ; extra == 'notebooks'
